formatflowed.py
formatflowed-2.0.0.dist-info/DESCRIPTION.rst
formatflowed-2.0.0.dist-info/METADATA
formatflowed-2.0.0.dist-info/RECORD
formatflowed-2.0.0.dist-info/WHEEL
formatflowed-2.0.0.dist-info/metadata.json
formatflowed-2.0.0.dist-info/top_level.txt
