Metadata-Version: 2.0
Name: formatflowed
Version: 2.0.0
Summary: RFC 3676 format=flowed text processing
Home-page: http://pypi.python.org/pypi/formatflowed
Author: Martijn Pieters
Author-email: mj@zopatista.com
License: Python Software Foundation License
Download-URL: http://www.zopatista.com/projects/formatflowed/releases/1.0.0/formatflowed-1.0.0.tar.gz
Keywords: email,mime,format,flowed,rfc2646,rfc3676
Platform: OS Independent
Classifier: Development Status :: 5 - Production/Stable
Classifier: Intended Audience :: Developers
Classifier: License :: OSI Approved :: Python Software Foundation License
Classifier: Operating System :: OS Independent
Classifier: Programming Language :: Python
Classifier: Programming Language :: Python :: 2.6
Classifier: Programming Language :: Python :: 2.7
Classifier: Programming Language :: Python :: 3.3
Classifier: Programming Language :: Python :: 3.4
Classifier: Programming Language :: Python :: 3.5
Classifier: Programming Language :: Python :: 3.6
Classifier: Programming Language :: Python :: Implementation :: PyPy
Classifier: Topic :: Communications :: Email
Classifier: Topic :: Software Development :: Libraries :: Python Modules
Classifier: Topic :: Text Processing :: Markup
Requires-Dist: setuptools
